arguments/__init__.py
config/__init__.py
config/credentials.py
gpt/__init__.py
gpt/request.py
gpt/util.py
qprom/__init__.py
qprom/main.py
qprom/utils.py
qprom-0.5.2.dist-info/LICENSE
qprom-0.5.2.dist-info/METADATA
qprom-0.5.2.dist-info/WHEEL
qprom-0.5.2.dist-info/entry_points.txt
qprom-0.5.2.dist-info/top_level.txt
qprom-0.5.2.dist-info/RECORD
