Metadata-Version: 2.1
Name: qprom
Version: 0.5.2
Summary: A Python-based CLI tool to quickly interact with OpenAIs GPT models instead of relying on the web interface.
Home-page: https://github.com/MartinWie/qprom
Download-URL: https://github.com/MartinWie/AEnv/archive/2.0.2.tar.gz
Author: MartinWiechmann
Author-email: donotsuspend@googlegroups.com
License: MIT
Keywords: GPT-4 CLI GPT-3 OpenAI
Classifier: Development Status :: 5 - Production/Stable
Classifier: Environment :: Console
Classifier: Intended Audience :: Developers
Classifier: License :: OSI Approved :: MIT License
Classifier: Programming Language :: Python :: 3
Classifier: Operating System :: OS Independent
License-File: LICENSE
Requires-Dist: tiktoken
Requires-Dist: openai
Requires-Dist: argparse
